Workbook

Sheet Sheet2
A3: Sum of Amount (₹) | B3: Column Labels
A4: Row Labels | B4: OpEx | C4: Overhead | D4: Revenue | E4: Target | F4: Grand Total
A5: Apr 2025 | B5: 487528 | C5: 156673 | D5: 1106901 | E5: 1782950 | F5: 3534052
A6: Bengaluru | B6: 181312 | C6: 54274 | D6: 420447 | E6: 667200 | F6: 1323233
A7: Hyderabad | B7: 140346 | C7: 43015 | D7: 313138 | E7: 499900 | F7: 996399
A8: Mumbai | B8: 165870 | C8: 59384 | D8: 373316 | E8: 615850 | F8: 1214420
A9: Feb 2025 | B9: 501150 | C9: 155458 | D9: 1103188 | E9: 1782950 | F9: 3542746
A10: Bengaluru | B10: 189358 | C10: 61254 | D10: 413792 | E10: 667200 | F10: 1331604
A11: Hyderabad | B11: 138932 | C11: 44420 | D11: 287379 | E11: 499900 | F11: 970631
A12: Mumbai | B12: 172860 | C12: 49784 | D12: 402017 | E12: 615850 | F12: 1240511
A13: Jan 2025 | B13: 482689 | C13: 155565 | D13: 1070013 | E13: 1782950 | F13: 3491217
A14: Bengaluru | B14: 180967 | C14: 58336 | D14: 404122 | E14: 667200 | F14: 1310625
A15: Hyderabad | B15: 137126 | C15: 43628 | D15: 313021 | E15: 499900 | F15: 993675
A16: Mumbai | B16: 164596 | C16: 53601 | D16: 352870 | E16: 615850 | F16: 1186917
... A29: Grand Total | B29: 2932437 | C29: 946843 | D29: 6620970 | E29: 10697700 | F29: 21197950

Sheet Sheet3
A3: Sum of Amount (₹) | B3: Column Labels
A4: Row Labels | B4: OpEx | C4: Overhead | D4: Revenue | E4: Target | F4: Grand Total
A5: Bengaluru | B5: 1079378 | C5: 359655 | D5: 2507382 | E5: 4003200 | F5: 7949615
A6: Hyderabad | B6: 832360 | C6: 262162 | D6: 1838084 | E6: 2999400 | F6: 5932006
A7: Mumbai | B7: 1020699 | C7: 325026 | D7: 2275504 | E7: 3695100 | F7: 7316329
A8: Grand Total | B8: 2932437 | C8: 946843 | D8: 6620970 | E8: 10697700 | F8: 21197950

Sheet Raw_Data
A1: Month | B1: City | C1: Type | D1: Sub-Category | E1: Amount (₹)
A2: Jan 2025 | B2: Bengaluru | C2: Revenue | D2: Ride Revenue | E2: 257856
A3: Jan 2025 | B3: Bengaluru | C3: Revenue | D3: Subscription Revenue | E3: 105735
A4: Jan 2025 | B4: Bengaluru | C4: Revenue | D4: Corporate Tie-ups | E4: 40531
A5: Jan 2025 | B5: Bengaluru | C5: OpEx | D5: Agent Payouts | E5: 85018
A6: Jan 2025 | B6: Bengaluru | C6: OpEx | D6: Maintenance & Repairs | E6: 61005
A7: Jan 2025 | B7: Bengaluru | C7: OpEx | D7: Fuel & Charging | E7: 34944
A8: Jan 2025 | B8: Bengaluru | C8: Overhead | D8: Office Rent | E8: 23482
A9: Jan 2025 | B9: Bengaluru | C9: Overhead | D9: Marketing Spend | E9: 21522
A10: Jan 2025 | B10: Bengaluru | C10: Overhead | D10: Software & Tools | E10: 13332
A11: Jan 2025 | B11: Bengaluru | C11: Target | D11: Revenue Target | E11: 441000
A12: Jan 2025 | B12: Bengaluru | C12: Target | D12: OpEx Target | E12: 171000
A13: Jan 2025 | B13: Bengaluru | C13: Target | D13: Overhead Target | E13: 55200
... A217: Jun 2025 | B217: Hyderabad | C217: Target | D217: Overhead Target | E217: 41400

Sheet Lookup_Table
A1: CATEGORY LOOKUP TABLE
A2: Sub-Category | B2: Type | C2: Cost Center | D2: Is_Revenue
A3: Ride Revenue | B3: Revenue | C3: Operations | D3: Yes
A4: Subscription Revenue | B4: Revenue | C4: Product | D4: Yes
A5: Corporate Tie-ups | B5: Revenue | C5: Sales | D5: Yes
A6: Agent Payouts | B6: OpEx | C6: HR/Ops | D6: No
A7: Maintenance & Repairs | B7: OpEx | C7: Engineering | D7: No
A8: Fuel & Charging | B8: OpEx | C8: Operations | D8: No
A9: Office Rent | B9: Overhead | C9: Admin | D9: No
A10: Marketing Spend | B10: Overhead | C10: Marketing | D10: No
A11: Software & Tools | B11: Overhead | C11: Tech | D11: No
A12: CITY REFERENCE
A13: City | B13: Zone | C13: Fleet Size | D13: Launch Year
A14: Bengaluru | B14: South | C14: 1200 | D14: 2022
A15: Mumbai | B15: West | C15: 980 | D15: 2023
A16: Hyderabad | B16: South | C16: 760 | D16: 2023

Sheet Summary
A1: YULU RIDES — FINANCIAL SUMMARY (JAN–JUN 2025)
A3: MONTHLY P&L OVERVIEW (₹)
A4: Category | B4: Jan 2025 | C4: Feb 2025 | D4: Mar 2025 | E4: Apr 2025 | F4: May 2025 | G4: Jun 2025
A5: Total Revenue | B5: =SUMIFS(Raw_Data!$E:$E,Raw_Data!$A:$A,Summary!B$4,Raw_Data!$C:$C,"Revenue") -> 1070013 | C5: =SUMIFS(Raw_Data!$E:$E,Raw_Data!$A:$A,Summary!C$4,Raw_Data!$C:$C,"Revenue") -> 1103188 | D5: =SUMIFS(Raw_Data!$E:$E,Raw_Data!$A:$A,Summary!D$4,Raw_Data!$C:$C,"Revenue") -> 1138553 | E5: =SUMIFS(Raw_Data!$E:$E,Raw_Data!$A:$A,Summary!E$4,Raw_Data!$C:$C,"Revenue") -> 1106901 | F5: =SUMIFS(Raw_Data!$E:$E,Raw_Data!$A:$A,Summary!F$4,Raw_Data!$C:$C,"Revenue") -> 1127042 | G5: =SUMIFS(Raw_Data!$E:$E,Raw_Data!$A:$A,Summary!G$4,Raw_Data!$C:$C,"Revenue") -> 1075273
A6: Total OpEx | B6: =SUMIFS(Raw_Data!$E:$E,Raw_Data!$A:$A,Summary!B$4,Raw_Data!$C:$C,"OpEx") -> 482689 | C6: =SUMIFS(Raw_Data!$E:$E,Raw_Data!$A:$A,Summary!C$4,Raw_Data!$C:$C,"OpEx") -> 501150 | D6: =SUMIFS(Raw_Data!$E:$E,Raw_Data!$A:$A,Summary!D$4,Raw_Data!$C:$C,"OpEx") -> 481385 | E6: =SUMIFS(Raw_Data!$E:$E,Raw_Data!$A:$A,Summary!E$4,Raw_Data!$C:$C,"OpEx") -> 487528 | F6: =SUMIFS(Raw_Data!$E:$E,Raw_Data!$A:$A,Summary!F$4,Raw_Data!$C:$C,"OpEx") -> 492704 | G6: =SUMIFS(Raw_Data!$E:$E,Raw_Data!$A:$A,Summary!G$4,Raw_Data!$C:$C,"OpEx") -> 486981
A7: Total Overhead | B7: =SUMIFS(Raw_Data!$E:$E,Raw_Data!$A:$A,Summary!B$4,Raw_Data!$C:$C,"Overhead") -> 155565 | C7: =SUMIFS(Raw_Data!$E:$E,Raw_Data!$A:$A,Summary!C$4,Raw_Data!$C:$C,"Overhead") -> 155458 | D7: =SUMIFS(Raw_Data!$E:$E,Raw_Data!$A:$A,Summary!D$4,Raw_Data!$C:$C,"Overhead") -> 160046 | E7: =SUMIFS(Raw_Data!$E:$E,Raw_Data!$A:$A,Summary!E$4,Raw_Data!$C:$C,"Overhead") -> 156673 | F7: =SUMIFS(Raw_Data!$E:$E,Raw_Data!$A:$A,Summary!F$4,Raw_Data!$C:$C,"Overhead") -> 159322 | G7: =SUMIFS(Raw_Data!$E:$E,Raw_Data!$A:$A,Summary!G$4,Raw_Data!$C:$C,"Overhead") -> 159779
A8: Gross Profit | B8: =B5-B6-B7 -> 431759 | C8: =C5-C6-C7 -> 446580 | D8: =D5-D6-D7 -> 497122 | E8: =E5-E6-E7 -> 462700 | F8: =F5-F6-F7 -> 475016 | G8: =G5-G6-G7 -> 428513
A9: Gross Margin % | B9: =IF(B5=0,0,B8/B5) -> 0.40350818 | C9: =IF(C5=0,0,C8/C5) -> 0.40480861 | D9: =IF(D5=0,0,D8/D5) -> 0.43662614 | E9: =IF(E5=0,0,E8/E5) -> 0.4180139 | F9: =IF(F5=0,0,F8/F5) -> 0.42147143 | G9: =IF(G5=0,0,G8/G5) -> 0.39851554
A11: CITY-WISE REVENUE vs TARGET (₹)
A12: City | B12: Actual Revenue | C12: Revenue Target | D12: Variance (₹) | E12: Variance % | F12: Status | G12: Cost Centre (VLOOKUP)
A13: Bengaluru | B13: =SUMIFS(Raw_Data!$E:$E,Raw_Data!$B:$B,A13,Raw_Data!$C:$C,"Revenue") -> 2507382 | C13: =SUMIFS(Raw_Data!$E:$E,Raw_Data!$B:$B,A13,Raw_Data!$C:$C,"Target",Raw_Data!$D:$D,"Revenue Target") -> 2646000 | D13: =B13-C13 -> -138618 | E13: =IF(C13=0,0,(B13-C13)/C13) -> -0.052387755 | F13: =IF(E13>=0,"✅ On Track","⚠️ Below Target") -> ⚠️ Below Target | G13: =INDEX(Lookup_Table!$B$14:$B$16,MATCH(A13,Lookup_Table!$A$14:$A$16,0)) -> South
A14: Mumbai | B14: =SUMIFS(Raw_Data!$E:$E,Raw_Data!$B:$B,A14,Raw_Data!$C:$C,"Revenue") -> 2275504 | C14: =SUMIFS(Raw_Data!$E:$E,Raw_Data!$B:$B,A14,Raw_Data!$C:$C,"Target",Raw_Data!$D:$D,"Revenue Target") -> 2394000 | D14: =B14-C14 -> -118496 | E14: =IF(C14=0,0,(B14-C14)/C14) -> -0.049497076 | F14: =IF(E14>=0,"✅ On Track","⚠️ Below Target") -> ⚠️ Below Target | G14: =INDEX(Lookup_Table!$B$14:$B$16,MATCH(A14,Lookup_Table!$A$14:$A$16,0)) -> West
A15: Hyderabad | B15: =SUMIFS(Raw_Data!$E:$E,Raw_Data!$B:$B,A15,Raw_Data!$C:$C,"Revenue") -> 1838084 | C15: =SUMIFS(Raw_Data!$E:$E,Raw_Data!$B:$B,A15,Raw_Data!$C:$C,"Target",Raw_Data!$D:$D,"Revenue Target") -> 1953000 | D15: =B15-C15 -> -114916 | E15: =IF(C15=0,0,(B15-C15)/C15) -> -0.058840758 | F15: =IF(E15>=0,"✅ On Track","⚠️ Below Target") -> ⚠️ Below Target | G15: =INDEX(Lookup_Table!$B$14:$B$16,MATCH(A15,Lookup_Table!$A$14:$A$16,0)) -> South
A17: VARIANCE ANALYSIS — ACTUAL vs TARGET (All Cities, All Months)
A18: Month | B18: Total Revenue | C18: Revenue Target | D18: Rev Variance | E18: Rev Var % | F18: Total OpEx | G18: OpEx Target | H18: OpEx Variance | I18: Flag
A19: Jan 2025 | B19: =SUMIFS(Raw_Data!$E:$E,Raw_Data!$A:$A,A19,Raw_Data!$C:$C,"Revenue") -> 1070013 | C19: =SUMIFS(Raw_Data!$E:$E,Raw_Data!$A:$A,A19,Raw_Data!$C:$C,"Target",Raw_Data!$D:$D,"Revenue Target") -> 1165500 | D19: =B19-C19 -> -95487 | E19: =IF(C19=0,0,(B19-C19)/C19) -> -0.081927928 | F19: =SUMIFS(Raw_Data!$E:$E,Raw_Data!$A:$A,A19,Raw_Data!$C:$C,"OpEx") -> 482689 | G19: =SUMIFS(Raw_Data!$E:$E,Raw_Data!$A:$A,A19,Raw_Data!$C:$C,"Target",Raw_Data!$D:$D,"OpEx Target") -> 470250 | H19: =G19-F19 -> -12439 | I19: =IF(OR(E19<-0.05,H19>0.05),"🚨 Review","✅ OK") -> 🚨 Review
A20: Feb 2025 | B20: =SUMIFS(Raw_Data!$E:$E,Raw_Data!$A:$A,A20,Raw_Data!$C:$C,"Revenue") -> 1103188 | C20: =SUMIFS(Raw_Data!$E:$E,Raw_Data!$A:$A,A20,Raw_Data!$C:$C,"Target",Raw_Data!$D:$D,"Revenue Target") -> 1165500 | D20: =B20-C20 -> -62312 | E20: =IF(C20=0,0,(B20-C20)/C20) -> -0.053463749 | F20: =SUMIFS(Raw_Data!$E:$E,Raw_Data!$A:$A,A20,Raw_Data!$C:$C,"OpEx") -> 501150 | G20: =SUMIFS(Raw_Data!$E:$E,Raw_Data!$A:$A,A20,Raw_Data!$C:$C,"Target",Raw_Data!$D:$D,"OpEx Target") -> 470250 | H20: =G20-F20 -> -30900 | I20: =IF(OR(E20<-0.05,H20>0.05),"🚨 Review","✅ OK") -> 🚨 Review
A21: Mar 2025 | B21: =SUMIFS(Raw_Data!$E:$E,Raw_Data!$A:$A,A21,Raw_Data!$C:$C,"Revenue") -> 1138553 | C21: =SUMIFS(Raw_Data!$E:$E,Raw_Data!$A:$A,A21,Raw_Data!$C:$C,"Target",Raw_Data!$D:$D,"Revenue Target") -> 1165500 | D21: =B21-C21 -> -26947 | E21: =IF(C21=0,0,(B21-C21)/C21) -> -0.023120549 | F21: =SUMIFS(Raw_Data!$E:$E,Raw_Data!$A:$A,A21,Raw_Data!$C:$C,"OpEx") -> 481385 | G21: =SUMIFS(Raw_Data!$E:$E,Raw_Data!$A:$A,A21,Raw_Data!$C:$C,"Target",Raw_Data!$D:$D,"OpEx Target") -> 470250 | H21: =G21-F21 -> -11135 | I21: =IF(OR(E21<-0.05,H21>0.05),"🚨 Review","✅ OK") -> ✅ OK
A22: Apr 2025 | B22: =SUMIFS(Raw_Data!$E:$E,Raw_Data!$A:$A,A22,Raw_Data!$C:$C,"Revenue") -> 1106901 | C22: =SUMIFS(Raw_Data!$E:$E,Raw_Data!$A:$A,A22,Raw_Data!$C:$C,"Target",Raw_Data!$D:$D,"Revenue Target") -> 1165500 | D22: =B22-C22 -> -58599 | E22: =IF(C22=0,0,(B22-C22)/C22) -> -0.050277992 | F22: =SUMIFS(Raw_Data!$E:$E,Raw_Data!$A:$A,A22,Raw_Data!$C:$C,"OpEx") -> 487528 | G22: =SUMIFS(Raw_Data!$E:$E,Raw_Data!$A:$A,A22,Raw_Data!$C:$C,"Target",Raw_Data!$D:$D,"OpEx Target") -> 470250 | H22: =G22-F22 -> -17278 | I22: =IF(OR(E22<-0.05,H22>0.05),"🚨 Review","✅ OK") -> 🚨 Review
A23: May 2025 | B23: =SUMIFS(Raw_Data!$E:$E,Raw_Data!$A:$A,A23,Raw_Data!$C:$C,"Revenue") -> 1127042 | C23: =SUMIFS(Raw_Data!$E:$E,Raw_Data!$A:$A,A23,Raw_Data!$C:$C,"Target",Raw_Data!$D:$D,"Revenue Target") -> 1165500 | D23: =B23-C23 -> -38458 | E23: =IF(C23=0,0,(B23-C23)/C23) -> -0.032996997 | F23: =SUMIFS(Raw_Data!$E:$E,Raw_Data!$A:$A,A23,Raw_Data!$C:$C,"OpEx") -> 492704 | G23: =SUMIFS(Raw_Data!$E:$E,Raw_Data!$A:$A,A23,Raw_Data!$C:$C,"Target",Raw_Data!$D:$D,"OpEx Target") -> 470250 | H23: =G23-F23 -> -22454 | I23: =IF(OR(E23<-0.05,H23>0.05),"🚨 Review","✅ OK") -> ✅ OK
A24: Jun 2025 | B24: =SUMIFS(Raw_Data!$E:$E,Raw_Data!$A:$A,A24,Raw_Data!$C:$C,"Revenue") -> 1075273 | C24: =SUMIFS(Raw_Data!$E:$E,Raw_Data!$A:$A,A24,Raw_Data!$C:$C,"Target",Raw_Data!$D:$D,"Revenue Target") -> 1165500 | D24: =B24-C24 -> -90227 | E24: =IF(C24=0,0,(B24-C24)/C24) -> -0.077414843 | F24: =SUMIFS(Raw_Data!$E:$E,Raw_Data!$A:$A,A24,Raw_Data!$C:$C,"OpEx") -> 486981 | G24: =SUMIFS(Raw_Data!$E:$E,Raw_Data!$A:$A,A24,Raw_Data!$C:$C,"Target",Raw_Data!$D:$D,"OpEx Target") -> 470250 | H24: =G24-F24 -> -16731 | I24: =IF(OR(E24<-0.05,H24>0.05),"🚨 Review","✅ OK") -> 🚨 Review

Sheet Dashboard
A1: 🚲 YULU RIDES | FINANCIAL PERFORMANCE DASHBOARD | H1 2025
A2: Data Source: Raw_Data sheet | Period: Jan–Jun 2025 | Cities: Bengaluru, Mumbai, Hyderabad
A4: KEY PERFORMANCE INDICATORS
A5: Total Revenue | C5: Total OpEx | E5: Total Overhead | G5: Gross Profit | I5: Gross Margin % | K5: Avg Monthly Revenue
A6: =SUMIFS(Raw_Data!$E:$E,Raw_Data!$C:$C,"Revenue") -> 6620970 | C6: =SUMIFS(Raw_Data!$E:$E,Raw_Data!$C:$C,"OpEx") -> 2932437 | E6: =SUMIFS(Raw_Data!$E:$E,Raw_Data!$C:$C,"Overhead") -> 946843 | G6: =Dashboard!B6-Dashboard!D6-Dashboard!F6 -> 0 | I6: =IF(B6=0,0,H6/B6) -> 0 | K6: =B6/6 -> 0
A9: MONTHLY TREND DATA (for charting)
A10: Month | B10: Revenue | C10: OpEx | D10: Overhead | E10: Gross Profit | F10: Margin % | G10: Rev Target
A11: Jan 2025 | B11: =SUMIFS(Raw_Data!$E:$E,Raw_Data!$A:$A,A11,Raw_Data!$C:$C,"Revenue") -> 1070013 | C11: =SUMIFS(Raw_Data!$E:$E,Raw_Data!$A:$A,A11,Raw_Data!$C:$C,"OpEx") -> 482689 | D11: =SUMIFS(Raw_Data!$E:$E,Raw_Data!$A:$A,A11,Raw_Data!$C:$C,"Overhead") -> 155565 | E11: =B11-C11-D11 -> 431759 | F11: =IF(B11=0,0,E11/B11) -> 0.40350818 | G11: =SUMIFS(Raw_Data!$E:$E,Raw_Data!$A:$A,A11,Raw_Data!$C:$C,"Target",Raw_Data!$D:$D,"Revenue Target") -> 1165500
A12: Feb 2025 | B12: =SUMIFS(Raw_Data!$E:$E,Raw_Data!$A:$A,A12,Raw_Data!$C:$C,"Revenue") -> 1103188 | C12: =SUMIFS(Raw_Data!$E:$E,Raw_Data!$A:$A,A12,Raw_Data!$C:$C,"OpEx") -> 501150 | D12: =SUMIFS(Raw_Data!$E:$E,Raw_Data!$A:$A,A12,Raw_Data!$C:$C,"Overhead") -> 155458 | E12: =B12-C12-D12 -> 446580 | F12: =IF(B12=0,0,E12/B12) -> 0.40480861 | G12: =SUMIFS(Raw_Data!$E:$E,Raw_Data!$A:$A,A12,Raw_Data!$C:$C,"Target",Raw_Data!$D:$D,"Revenue Target") -> 1165500
A13: Mar 2025 | B13: =SUMIFS(Raw_Data!$E:$E,Raw_Data!$A:$A,A13,Raw_Data!$C:$C,"Revenue") -> 1138553 | C13: =SUMIFS(Raw_Data!$E:$E,Raw_Data!$A:$A,A13,Raw_Data!$C:$C,"OpEx") -> 481385 | D13: =SUMIFS(Raw_Data!$E:$E,Raw_Data!$A:$A,A13,Raw_Data!$C:$C,"Overhead") -> 160046 | E13: =B13-C13-D13 -> 497122 | F13: =IF(B13=0,0,E13/B13) -> 0.43662614 | G13: =SUMIFS(Raw_Data!$E:$E,Raw_Data!$A:$A,A13,Raw_Data!$C:$C,"Target",Raw_Data!$D:$D,"Revenue Target") -> 1165500
A14: Apr 2025 | B14: =SUMIFS(Raw_Data!$E:$E,Raw_Data!$A:$A,A14,Raw_Data!$C:$C,"Revenue") -> 1106901 | C14: =SUMIFS(Raw_Data!$E:$E,Raw_Data!$A:$A,A14,Raw_Data!$C:$C,"OpEx") -> 487528 | D14: =SUMIFS(Raw_Data!$E:$E,Raw_Data!$A:$A,A14,Raw_Data!$C:$C,"Overhead") -> 156673 | E14: =B14-C14-D14 -> 462700 | F14: =IF(B14=0,0,E14/B14) -> 0.4180139 | G14: =SUMIFS(Raw_Data!$E:$E,Raw_Data!$A:$A,A14,Raw_Data!$C:$C,"Target",Raw_Data!$D:$D,"Revenue Target") -> 1165500
A15: May 2025 | B15: =SUMIFS(Raw_Data!$E:$E,Raw_Data!$A:$A,A15,Raw_Data!$C:$C,"Revenue") -> 1127042 | C15: =SUMIFS(Raw_Data!$E:$E,Raw_Data!$A:$A,A15,Raw_Data!$C:$C,"OpEx") -> 492704 | D15: =SUMIFS(Raw_Data!$E:$E,Raw_Data!$A:$A,A15,Raw_Data!$C:$C,"Overhead") -> 159322 | E15: =B15-C15-D15 -> 475016 | F15: =IF(B15=0,0,E15/B15) -> 0.42147143 | G15: =SUMIFS(Raw_Data!$E:$E,Raw_Data!$A:$A,A15,Raw_Data!$C:$C,"Target",Raw_Data!$D:$D,"Revenue Target") -> 1165500
A16: Jun 2025 | B16: =SUMIFS(Raw_Data!$E:$E,Raw_Data!$A:$A,A16,Raw_Data!$C:$C,"Revenue") -> 1075273 | C16: =SUMIFS(Raw_Data!$E:$E,Raw_Data!$A:$A,A16,Raw_Data!$C:$C,"OpEx") -> 486981 | D16: =SUMIFS(Raw_Data!$E:$E,Raw_Data!$A:$A,A16,Raw_Data!$C:$C,"Overhead") -> 159779 | E16: =B16-C16-D16 -> 428513 | F16: =IF(B16=0,0,E16/B16) -> 0.39851554 | G16: =SUMIFS(Raw_Data!$E:$E,Raw_Data!$A:$A,A16,Raw_Data!$C:$C,"Target",Raw_Data!$D:$D,"Revenue Target") -> 1165500
A19: CITY PERFORMANCE SNAPSHOT
A20: City | B20: 6M Revenue | C20: 6M OpEx | D20: 6M Overhead | E20: Gross Profit | F20: Margin % | G20: Fleet Size (Lookup)
A21: Bengaluru | B21: =SUMIFS(Raw_Data!$E:$E,Raw_Data!$B:$B,A21,Raw_Data!$C:$C,"Revenue") -> 2507382 | C21: =SUMIFS(Raw_Data!$E:$E,Raw_Data!$B:$B,A21,Raw_Data!$C:$C,"OpEx") -> 1079378 | D21: =SUMIFS(Raw_Data!$E:$E,Raw_Data!$B:$B,A21,Raw_Data!$C:$C,"Overhead") -> 359655 | E21: =B21-C21-D21 -> 1068349 | F21: =IF(B21=0,0,E21/B21) -> 0.42608147 | G21: =INDEX(Lookup_Table!$C$14:$C$16,MATCH(A21,Lookup_Table!$A$14:$A$16,0)) -> 1200
A22: Mumbai | B22: =SUMIFS(Raw_Data!$E:$E,Raw_Data!$B:$B,A22,Raw_Data!$C:$C,"Revenue") -> 2275504 | C22: =SUMIFS(Raw_Data!$E:$E,Raw_Data!$B:$B,A22,Raw_Data!$C:$C,"OpEx") -> 1020699 | D22: =SUMIFS(Raw_Data!$E:$E,Raw_Data!$B:$B,A22,Raw_Data!$C:$C,"Overhead") -> 325026 | E22: =B22-C22-D22 -> 929779 | F22: =IF(B22=0,0,E22/B22) -> 0.40860354 | G22: =INDEX(Lookup_Table!$C$14:$C$16,MATCH(A22,Lookup_Table!$A$14:$A$16,0)) -> 980
A23: Hyderabad | B23: =SUMIFS(Raw_Data!$E:$E,Raw_Data!$B:$B,A23,Raw_Data!$C:$C,"Revenue") -> 1838084 | C23: =SUMIFS(Raw_Data!$E:$E,Raw_Data!$B:$B,A23,Raw_Data!$C:$C,"OpEx") -> 832360 | D23: =SUMIFS(Raw_Data!$E:$E,Raw_Data!$B:$B,A23,Raw_Data!$C:$C,"Overhead") -> 262162 | E23: =B23-C23-D23 -> 743562 | F23: =IF(B23=0,0,E23/B23) -> 0.40453102 | G23: =INDEX(Lookup_Table!$C$14:$C$16,MATCH(A23,Lookup_Table!$A$14:$A$16,0)) -> 760
A25: 📌 HOW TO BUILD YOUR CHARTS (Step 5 of the Build Guide)
A26: 1. Select A10:B16 → Insert → Line/Column Chart → 'Monthly Revenue Trend'
A27: 2. Select A10:E16 → Insert → Stacked Column Chart → 'Revenue vs Cost Breakdown'
A28: 3. Select A10:A16 + F10:F16 → Insert → Line Chart → 'Gross Margin % by Month'
A29: 4. Select A21:B23 → Insert → Pie/Donut Chart → 'Revenue by City'
A30: 5. Add slicers: select any SUMIFS cell → Insert → Slicer (connect to Raw_Data table)
A31: 6. Right-click each chart → Move Chart → to this Dashboard sheet
